cspyk/__init__.py
cspyk/kernelapp.py
cspyk/provisioning.py
cspyk/provisioning_local.py
cspyk-0.1.0.dist-info/licenses/LICENSE
cspyk-0.1.0.dist-info/METADATA
cspyk-0.1.0.dist-info/WHEEL
cspyk-0.1.0.dist-info/entry_points.txt
cspyk-0.1.0.dist-info/top_level.txt
cspyk-0.1.0.dist-info/RECORD
