Metadata-Version: 2.4
Name: cspyk
Version: 0.1.0
Summary: Jupyter kernel provisioner package for Cybershuttle
Author: Dimuthu Wannipurage
License: Apache-2
Classifier: Topic :: Utilities
Classifier: Framework :: Jupyter
Requires-Python: >=3.8
License-File: LICENSE
Requires-Dist: jupyter-client>=7.0
Dynamic: license-file
